pygments_systemrdl-1.3.0.dist-info/licenses/LICENSE
rdl_pygments/__about__.py
rdl_pygments/__init__.py
rdl_pygments/rdllexer.py
pygments_systemrdl-1.3.0.dist-info/METADATA
pygments_systemrdl-1.3.0.dist-info/WHEEL
pygments_systemrdl-1.3.0.dist-info/entry_points.txt
pygments_systemrdl-1.3.0.dist-info/top_level.txt
pygments_systemrdl-1.3.0.dist-info/RECORD
