Metadata-Version: 2.4
Name: pygments-systemrdl
Version: 1.3.0
Summary: SystemRDL 2.0 lexer extension for Pygments
Author: Alex Mykyta
License: LGPLv3
Project-URL: Source, https://github.com/SystemRDL/systemrdl-pygments
Project-URL: Tracker, https://github.com/SystemRDL/systemrdl-pygments/issues
Project-URL: Changelog, https://github.com/SystemRDL/systemrdl-pygments/releases
Keywords: SystemRDL,pygments
Classifier: Development Status :: 5 - Production/Stable
Classifier: Programming Language :: Python
Classifier: Programming Language :: Python :: 3
Classifier: Programming Language :: Python :: 3 :: Only
Classifier: Intended Audience :: Developers
Classifier: License :: OSI Approved :: GNU General Public License v3 (GPLv3)
Classifier: Operating System :: OS Independent
Requires-Python: >=3.7
License-File: LICENSE
Requires-Dist: pygments
Dynamic: license-file
